{"逐光之石": "行者之心", "异国之盏": "行者之心", "归乡之羽": "行者之心", "感别之冠": "行者之心", "故人之心": "行者之心", "勇士的壮行": "勇士之心", "勇士的期许": "勇士之心", "勇士的冠冕": "勇士之心", "勇士的勋章": "勇士之心", "勇士的坚毅": "勇士之心", "守护之皿": "守护之心", "守护徽印": "守护之心", "守护束带": "守护之心", "守护之花": "守护之心", "守护座钟": "守护之心", "奇迹之杯": "奇迹", "奇迹之羽": "奇迹", "奇迹耳坠": "奇迹", "奇迹之花": "奇迹", "奇迹之沙": "奇迹", "战狂的骨杯": "战狂", "战狂的翎羽": "战狂", "战狂的鬼面": "战狂", "战狂的蔷薇": "战狂", "战狂的时计": "战狂", "武人的酒杯": "武人", "武人的羽饰": "武人", "武人的头巾": "武人", "武人的红花": "武人", "武人的水漏": "武人", "教官的茶杯": "教官", "教官的羽饰": "教官", "教官的帽子": "教官", "教官的胸花": "教官", "教官的怀表": "教官", "赌徒的骰盅": "赌徒", "赌徒的羽饰": "赌徒", "赌徒的耳环": "赌徒", "赌徒的胸花": "赌徒", "赌徒的怀表": "赌徒", "流放者之杯": "流放者", "流放者之羽": "流放者", "流放者头冠": "流放者", "流放者之花": "流放者", "流放者怀表": "流放者", "冒险家金杯": "冒险家", "冒险家尾羽": "冒险家", "冒险家头带": "冒险家", "冒险家之花": "冒险家", "冒险家怀表": "冒险家", "幸运儿之杯": "幸运儿", "幸运儿鹰羽": "幸运儿", "幸运儿银冠": "幸运儿", "幸运儿绿花": "幸运儿", "幸运儿沙漏": "幸运儿", "学士的墨杯": "学士", "学士的羽笔": "学士", "学士的镜片": "学士", "学士的书签": "学士", "学士的时钟": "学士", "游医的药壶": "游医", "游医的枭羽": "游医", "游医的方巾": "游医", "游医的银莲": "游医", "游医的怀钟": "游医", "遍结寒霜的傲骨": "冰风迷途的勇士", "摧冰而行的执望": "冰风迷途的勇士", "破冰踏雪的回音": "冰风迷途的勇士", "历经风雪的思念": "冰风迷途的勇士", "冰雪故园的终期": "冰风迷途的勇士", "平雷之器": "平息鸣雷的尊者", "平雷之羽": "平息鸣雷的尊者", "平雷之冠": "平息鸣雷的尊者", "平雷之心": "平息鸣雷的尊者", "平雷之刻": "平息鸣雷的尊者", "渡火者的醒悟": "渡过烈火的贤人", "渡火者的解脱": "渡过烈火的贤人", "渡火者的智慧": "渡过烈火的贤人", "渡火者的决绝": "渡过烈火的贤人", "渡火者的煎熬": "渡过烈火的贤人", "少女片刻的闲暇": "被怜爱的少女", "少女飘摇的思念": "被怜爱的少女", "少女易逝的芳颜": "被怜爱的少女", "远方的少女之心": "被怜爱的少女", "少女苦短的良辰": "被怜爱的少女", "角斗士的酣醉": "角斗士的终幕礼", "角斗士的归宿": "角斗士的终幕礼", "角斗士的凯旋": "角斗士的终幕礼", "角斗士的留恋": "角斗士的终幕礼", "角斗士的希冀": "角斗士的终幕礼", "翠绿猎人的容器": "翠绿之影", "猎人青翠的箭羽": "翠绿之影", "翠绿的猎人之冠": "翠绿之影", "野花记忆的绿野": "翠绿之影", "翠绿猎人的笃定": "翠绿之影", "吟游者之壶": "流浪大地的乐团", "琴师的箭羽": "流浪大地的乐团", "指挥的礼帽": "流浪大地的乐团", "乐团的晨光": "流浪大地的乐团", "终幕的时计": "流浪大地的乐团", "北风之盏": "冰之川与雪之砂", "雪藏之羽": "冰之川与雪之砂", "冰河之冠": "冰之川与雪之砂", "凛冬霜心": "冰之川与雪之砂", "凝冰成砂": "冰之川与雪之砂", "降雷的凶兆": "如雷的盛怒", "雷灾的孑遗": "如雷的盛怒", "唤雷的头冠": "如雷的盛怒", "雷鸟的怜悯": "如雷的盛怒", "雷霆的时计": "如雷的盛怒", "魔女的心之火": "炽烈的炎之魔女", "魔女常燃之羽": "炽烈的炎之魔女", "焦灼的魔女帽": "炽烈的炎之魔女", "魔女的炎之花": "炽烈的炎之魔女", "魔女破灭之时": "炽烈的炎之魔女", "宗室银瓮": "昔日宗室之仪", "宗室之翎": "昔日宗室之仪", "宗室面具": "昔日宗室之仪", "宗室之花": "昔日宗室之仪", "宗室时计": "昔日宗室之仪", "染血骑士之杯": "染血的骑士道", "染血的黑之羽": "染血的骑士道", "染血的铁假面": "染血的骑士道", "染血的铁之心": "染血的骑士道", "骑士染血之时": "染血的骑士道", "祭火礼冠": "祭火之人", "祭水礼冠": "祭水之人", "祭雷礼冠": "祭雷之人", "祭风礼冠": "祭风之人", "祭冰礼冠": "祭冰之人", "巉岩琢塑之樽": "悠古的磐岩", "嵯峨群峰之翼": "悠古的磐岩", "不动玄石之相": "悠古的磐岩", "磐陀裂生之花": "悠古的磐岩", "星罗圭璧之晷": "悠古的磐岩", "夏祭水玉": "逆飞的流星", "夏祭终末": "逆飞的流星", "夏祭之面": "逆飞的流星", "夏祭之花": "逆飞的流星", "夏祭之刻": "逆飞的流星", "沉波之盏": "沉沦之心", "追忆之风": "沉沦之心", "酒渍船帽": "沉沦之心", "饰金胸花": "沉沦之心", "坚铜罗盘": "沉沦之心", "盟誓金爵": "千岩牢固", "昭武翎羽": "千岩牢固", "将帅兜鍪": "千岩牢固", "勋绩之花": "千岩牢固", "金铜时晷": "千岩牢固", "超越之盏": "苍白之火", "贤医之羽": "苍白之火", "嗤笑之面": "苍白之火", "无垢之花": "苍白之火", "停摆之刻": "苍白之火", "祈望之心": "追忆之注连", "思忆之矢": "追忆之注连", "无常之面": "追忆之注连", "羁缠之花": "追忆之注连", "朝露之时": "追忆之注连", "绯花之壶": "绝缘之旗印", "切落之羽": "绝缘之旗印", "华饰之兜": "绝缘之旗印", "明威之镡": "绝缘之旗印", "雷云之笼": "绝缘之旗印", "梦醒之瓢": "华馆梦醒形骸记", "华馆之羽": "华馆梦醒形骸记", "形骸之笠": "华馆梦醒形骸记", "荣花之期": "华馆梦醒形骸记", "众生之谣": "华馆梦醒形骸记", "真珠之笼": "海染砗磲", "渊宫之羽": "海染砗磲", "海祇之冠": "海染砗磲", "海染之花": "海染砗磲", "离别之贝": "海染砗磲", "结契之刻": "辰砂往生录", "潜光片羽": "辰砂往生录", "虺雷之姿": "辰砂往生录", "生灵之华": "辰砂往生录", "阳辔之遗": "辰砂往生录", "涌泉之盏": "来歆余响", "垂玉之叶": "来歆余响", "浮溯之珏": "来歆余响", "魂香之花": "来歆余响", "祝祀之凭": "来歆余响", "迷误者之灯": "深林的记忆", "翠蔓的智者": "深林的记忆", "月桂的宝冠": "深林的记忆", "迷宫的游人": "深林的记忆", "贤智的定期": "深林的记忆", "如蜜的终宴": "饰金之梦", "裁断的翎羽": "饰金之梦", "沙王的投影": "饰金之梦", "梦中的铁花": "饰金之梦", "沉金的岁月": "饰金之梦", "迷醉长梦的守护": "沙上楼阁史话", "黄金邦国的结末": "沙上楼阁史话", "流沙贵嗣的遗宝": "沙上楼阁史话", "众王之都的开端": "沙上楼阁史话", "失落迷途的机芯": "沙上楼阁史话", "守秘的魔瓶": "乐园遗落之花", "谢落的筵席": "乐园遗落之花", "紫晶的花冠": "乐园遗落之花", "月女的华彩": "乐园遗落之花", "凝结的时刻": "乐园遗落之花", "勇者们的茶会": "水仙之梦", "坏巫师的羽杖": "水仙之梦", "恶龙的单片镜": "水仙之梦", "旅途中的鲜花": "水仙之梦", "水仙的时时刻刻": "水仙之梦", "无边酣乐之筵": "花海甘露之光", "琦色灵彩之羽": "花海甘露之光", "灵光明烁之心": "花海甘露之光", "灵光源起之蕊": "花海甘露之光", "久远花落之时": "花海甘露之光", "遗忘的容器": "逐影猎人", "杰作的序曲": "逐影猎人", "老兵的容颜": "逐影猎人", "猎人的胸花": "逐影猎人", "裁判的时刻": "逐影猎人", "黄金之夜的喧嚣": "黄金剧团", "黄金飞鸟的落羽": "黄金剧团", "黄金剧团的奖赏": "黄金剧团", "黄金乐曲的变奏": "黄金剧团", "黄金时代的先声": "黄金剧团", "昔时应许之梦": "昔时之歌", "昔时浮想之思": "昔时之歌", "昔时传奏之诗": "昔时之歌", "昔时遗落之誓": "昔时之歌", "昔时回映之音": "昔时之歌", "慷慨的墨水瓶": "回声之林夜话", "诚恳的蘸水笔": "回声之林夜话", "慈爱的淑女帽": "回声之林夜话", "无私的妆饰花": "回声之林夜话", "忠实的砂时计": "回声之林夜话", "灵露倾洒的狂诗": "谐律异想断章", "古海玄幽的夜想": "谐律异想断章", "异想零落的圆舞": "谐律异想断章", "谐律交响的前奏": "谐律异想断章", "命途轮转的谐谑": "谐律异想断章", "筹谋的共樽": "未竟的遐思", "褪光的翠尾": "未竟的遐思", "失冕的宝冠": "未竟的遐思", "暗结的明花": "未竟的遐思", "举业的识刻": "未竟的遐思", "游学者的爪杯": "烬城勇者绘卷", "巡山客的信标": "烬城勇者绘卷", "魔战士的羽面": "烬城勇者绘卷", "驯兽师的护符": "烬城勇者绘卷", "秘术家的金盘": "烬城勇者绘卷", "纷争的前宴": "黑曜秘典", "灵髓的根脉": "黑曜秘典", "诸圣的礼冠": "黑曜秘典", "异种的期许": "黑曜秘典", "夜域的迷思": "黑曜秘典"}